mavenn/__init__.py
mavenn/examples/__init__.py
mavenn/examples/datasets/amyloid_data.csv.gz
mavenn/examples/datasets/gb1_data.csv.gz
mavenn/examples/datasets/mpsa_data.csv.gz
mavenn/examples/datasets/mpsa_replicate_data.csv.gz
mavenn/examples/datasets/nisthal_data.csv.gz
mavenn/examples/datasets/sortseq_data.csv.gz
mavenn/examples/datasets/tdp43_data.csv.gz
mavenn/examples/demos/gb1_ge_evaluation.py
mavenn/examples/demos/mpsa_ge_training.py
mavenn/examples/demos/sortseq_mpa_visualization.py
mavenn/examples/models/gb1_ge_additive.pickle
mavenn/examples/models/gb1_ge_additive.weights.h5
mavenn/examples/models/mpsa_ge_pairwise.pickle
mavenn/examples/models/mpsa_ge_pairwise.weights.h5
mavenn/examples/models/sortseq_mpa_additive.pickle
mavenn/examples/models/sortseq_mpa_additive.weights.h5
mavenn/examples/tutorials/1_demos.ipynb
mavenn/examples/tutorials/2_protein_dms_additive_gpmaps.ipynb
mavenn/examples/tutorials/3_splicing_mpra_multiple_gpmaps.ipynb
mavenn/examples/tutorials/4_protein_dms_biohysical_gpmap.ipynb
mavenn/examples/tutorials/5_promoter_biophysical_gpmaps.ipynb
mavenn/src/__init__.py
mavenn/src/_npeet.py
mavenn/src/callbacks.py
mavenn/src/entropy.py
mavenn/src/error_handling.py
mavenn/src/examples.py
mavenn/src/mavedb.py
mavenn/src/metrics.py
mavenn/src/model.py
mavenn/src/regression_types.py
mavenn/src/reshape.py
mavenn/src/utils.py
mavenn/src/validate.py
mavenn/src/visualization.py
mavenn/src/dev/__init__.py
mavenn/src/dev/landscape.py
mavenn/src/layers/__init__.py
mavenn/src/layers/gpmap.py
mavenn/src/layers/measurement_process_layers.py
mavenn/tests/__init__.py
mavenn/tests/specific_tests.py
mavenn/tests/testing_utils.py
mavenn_acordero-1.1.5.dist-info/METADATA
mavenn_acordero-1.1.5.dist-info/WHEEL
mavenn_acordero-1.1.5.dist-info/licenses/LICENSE
mavenn_acordero-1.1.5.dist-info/RECORD
