Metadata-Version: 2.4
Name: mavenn_acordero
Version: 1.1.5
Summary: MAVE-NN: learning genotype-phenotype maps from multiplex assays of variant effect
Project-URL: Documentation, https://mavenn.readthedocs.io/en/v1.1.2/
Project-URL: Repository, https://github.com/jbkinney/mavenn
Author-email: "Ammar Tareen and Justin B. Kinney" <jkinney@cshl.edu>
License: The MIT License (MIT)
License-File: LICENSE
Keywords: deep mutational scanning,genotype-phenotype maps,massively parallel reporter assays,multiplex assays,variant effect
Classifier: Development Status :: 3 - Alpha
Classifier: License :: OSI Approved :: MIT License
Classifier: Programming Language :: Python :: 3.12
Classifier: Topic :: Scientific/Engineering :: Bio-Informatics
Requires-Python: >=3.8
Requires-Dist: logomaker
Requires-Dist: matplotlib
Requires-Dist: numpy
Requires-Dist: pandas
Requires-Dist: scikit-learn
Requires-Dist: scipy
Requires-Dist: seaborn
Requires-Dist: tensorflow
